rapidq/__init__.py
rapidq/__main__.py
rapidq/broker/__init__.py
rapidq/broker/base.py
rapidq/broker/redis_broker.py
rapidq/constants.py
rapidq/decorators.py
rapidq/master.py
rapidq/message.py
rapidq/registry.py
rapidq/startup.py
rapidq/utils.py
rapidq/worker/__init__.py
rapidq/worker/process_worker.py
rapidq-0.3.0.dist-info/entry_points.txt
rapidq-0.3.0.dist-info/LICENSE
rapidq-0.3.0.dist-info/METADATA
rapidq-0.3.0.dist-info/WHEEL
rapidq-0.3.0.dist-info/RECORD
