Metadata-Version: 2.3
Name: RapidQ
Version: 0.3.0
Summary: A lightweight and fast background task processing library for Python, developed with simplicity in mind.
License: BSD-3-Clause
Keywords: multiprocessing,task-queue,task-manager
Author: Yaswanth C
Author-email: yaswanthc.dev@gmail.com
Requires-Python: >=3.10
Classifier: Development Status :: 3 - Alpha
Classifier: Intended Audience :: Developers
Classifier: License :: OSI Approved :: BSD License
Classifier: Operating System :: OS Independent
Classifier: Programming Language :: Python
Classifier: Programming Language :: Python :: 3
Classifier: Programming Language :: Python :: 3.10
Classifier: Programming Language :: Python :: 3.11
Classifier: Programming Language :: Python :: 3.12
Classifier: Programming Language :: Python :: 3.13
Classifier: Programming Language :: Python :: 3 :: Only
Classifier: Topic :: Software Development :: Object Brokering
Requires-Dist: redis (==5.2.1)
Project-URL: Homepage, https://github.com/Yaswanth-C/RapidQ
Project-URL: Repository, https://github.com/Yaswanth-C/RapidQ
